MANIFEST.in
README.md
setup.py
biowardrobe_airflow_plugins/.git_version
biowardrobe_airflow_plugins/__init__.py
biowardrobe_airflow_plugins/create_plugin.py
biowardrobe_airflow_plugins/init_plugin.py
biowardrobe_airflow_plugins.egg-info/PKG-INFO
biowardrobe_airflow_plugins.egg-info/SOURCES.txt
biowardrobe_airflow_plugins.egg-info/dependency_links.txt
biowardrobe_airflow_plugins.egg-info/entry_points.txt
biowardrobe_airflow_plugins.egg-info/not-zip-safe
biowardrobe_airflow_plugins.egg-info/requires.txt
biowardrobe_airflow_plugins.egg-info/top_level.txt
biowardrobe_airflow_plugins/cwls/plot-dna.cwl
biowardrobe_airflow_plugins/cwls/plot-rna.cwl
biowardrobe_airflow_plugins/cwls/satscript.cwl
biowardrobe_airflow_plugins/cwls/super-enhancer.cwl
biowardrobe_airflow_plugins/operators/__init__.py
biowardrobe_airflow_plugins/operators/biowardrobepluginjobdispatcher.py
biowardrobe_airflow_plugins/operators/biowardrobepluginjobgatherer.py
biowardrobe_airflow_plugins/operators/biowardrobeplugintrigger.py
biowardrobe_airflow_plugins/sql_patches/biowardrobe/plugintype_create.sql
biowardrobe_airflow_plugins/sql_patches/biowardrobe/plugintype_patch.sql
biowardrobe_airflow_plugins/sql_patches/genome_browser/dm3_view_patch.sql
biowardrobe_airflow_plugins/sql_patches/genome_browser/hg19_view_patch.sql
biowardrobe_airflow_plugins/sql_patches/genome_browser/mm10_view_patch.sql
biowardrobe_airflow_plugins/sql_patches/genome_browser/rheMac8_view_patch.sql
biowardrobe_airflow_plugins/sql_patches/genome_browser/rn5_view_patch.sql
biowardrobe_airflow_plugins/sql_patches/genome_browser/xenLae9_view_patch.sql
biowardrobe_airflow_plugins/sql_patches/genome_browser/xenTro3_view_patch.sql
biowardrobe_airflow_plugins/sql_patches/genome_browser/xenTro7_1_view_patch.sql
biowardrobe_airflow_plugins/sql_patches/genome_browser/xenTro9_view_patch.sql
biowardrobe_airflow_plugins/templates/__init__.py
biowardrobe_airflow_plugins/templates/outputs.py
biowardrobe_airflow_plugins/utils/__init__.py
biowardrobe_airflow_plugins/utils/analyze.py
biowardrobe_airflow_plugins/utils/connect.py
biowardrobe_airflow_plugins/utils/func.py
biowardrobe_airflow_plugins/utils/upload.py